cbftorch/__init__.py
cbftorch/barriers/__init__.py
cbftorch/barriers/backup_barrier.py
cbftorch/barriers/barrier.py
cbftorch/barriers/composite_barrier.py
cbftorch/barriers/multi_barrier.py
cbftorch/safe_controls/__init__.py
cbftorch/safe_controls/backup_safe_control.py
cbftorch/safe_controls/base_safe_control.py
cbftorch/safe_controls/closed_form_safe_control.py
cbftorch/safe_controls/qp_safe_control.py
cbftorch/utils/__init__.py
cbftorch/utils/dynamics.py
cbftorch/utils/make_map.py
cbftorch/utils/utils.py
cbftorch-0.1.1.dist-info/licenses/LICENSE
cbftorch-0.1.1.dist-info/METADATA
cbftorch-0.1.1.dist-info/WHEEL
cbftorch-0.1.1.dist-info/top_level.txt
cbftorch-0.1.1.dist-info/RECORD
