Metadata-Version: 2.4
Name: cbftorch
Version: 0.1.1
Summary: A PyTorch-based library for Control Barrier Functions (CBF) and safe control
Home-page: https://github.com/pedramrabiee/cbftorch
Author: Pedram Rabiee
Author-email: Pedram Rabiee <pedram.rabiee@gmail.com>
License: MIT
Project-URL: Homepage, https://github.com/pedramrabiee/cbftorch
Project-URL: Documentation, https://github.com/pedramrabiee/cbftorch#readme
Project-URL: Repository, https://github.com/pedramrabiee/cbftorch
Project-URL: Bug Tracker, https://github.com/pedramrabiee/cbftorch/issues
Keywords: control barrier functions,safe control,pytorch,robotics,control theory
Classifier: Programming Language :: Python :: 3
Classifier: Programming Language :: Python :: 3.7
Classifier: Programming Language :: Python :: 3.8
Classifier: Programming Language :: Python :: 3.9
Classifier: Programming Language :: Python :: 3.10
Classifier: Programming Language :: Python :: 3.11
Classifier: License :: OSI Approved :: MIT License
Classifier: Operating System :: OS Independent
Classifier: Development Status :: 3 - Alpha
Classifier: Intended Audience :: Science/Research
Classifier: Topic :: Scientific/Engineering :: Artificial Intelligence
Classifier: Topic :: Scientific/Engineering :: Mathematics
Requires-Python: >=3.7
License-File: LICENSE
Requires-Dist: torch>=1.9.0
Requires-Dist: numpy>=1.19.0
Requires-Dist: torchdiffeq>=0.2.0
Requires-Dist: cvxopt>=1.2.0
Requires-Dist: matplotlib>=3.3.0
Requires-Dist: Pillow>=8.0.0
Requires-Dist: python-box>=5.0.0
Requires-Dist: qpth>=0.0.15
Requires-Dist: opencv-python>=4.5.0
Dynamic: license-file
